<annotation>
	<folder>05 Truck</folder>
	<filename>IMG_4004.jpeg</filename>
	<path>D:\KICE\010 Project KICE\025 Smart Parking\Pictures\05 Truck\IMG_4004.jpeg</path>
	<source>
		<database>Unknown</database>
	</source>
	<size>
		<width>800</width>
		<height>450</height>
		<depth>3</depth>
	</size>
	<segmented>0</segmented>
	<object>
		<name>truck</name>
		<pose>Unspecified</pose>
		<truncated>0</truncated>
		<difficult>0</difficult>
		<bndbox>
			<xmin>6</xmin>
			<ymin>72</ymin>
			<xmax>779</xmax>
			<ymax>402</ymax>
		</bndbox>
	</object>
</annotation>
