<annotation>
	<folder>06-Bus</folder>
	<filename>IMG_5136.jpg</filename>
	<path>D:\KICE\010 Project KICE\025 Smart Parking\Pictures\06-Bus\IMG_5136.jpg</path>
	<source>
		<database>Unknown</database>
	</source>
	<size>
		<width>1500</width>
		<height>1051</height>
		<depth>3</depth>
	</size>
	<segmented>0</segmented>
	<object>
		<name>bus</name>
		<pose>Unspecified</pose>
		<truncated>0</truncated>
		<difficult>0</difficult>
		<bndbox>
			<xmin>361</xmin>
			<ymin>147</ymin>
			<xmax>1242</xmax>
			<ymax>823</ymax>
		</bndbox>
	</object>
</annotation>
