<annotation>
	<folder>01 Motorcycle</folder>
	<filename>IMG_066.jpg</filename>
	<path>D:\KICE\010 Project KICE\025 Smart Parking\Pictures\01 Motorcycle\IMG_066.jpg</path>
	<source>
		<database>Unknown</database>
	</source>
	<size>
		<width>1000</width>
		<height>563</height>
		<depth>3</depth>
	</size>
	<segmented>0</segmented>
	<object>
		<name>motorcycle</name>
		<pose>Unspecified</pose>
		<truncated>0</truncated>
		<difficult>0</difficult>
		<bndbox>
			<xmin>203</xmin>
			<ymin>33</ymin>
			<xmax>790</xmax>
			<ymax>503</ymax>
		</bndbox>
	</object>
</annotation>
